df_compare_pl/__init__.py
df_compare_pl/df_compare_pl.py
df_compare_pl/py.typed
df_compare_pl-0.2.dist-info/METADATA
df_compare_pl-0.2.dist-info/WHEEL
df_compare_pl-0.2.dist-info/licenses/LICENSE
df_compare_pl-0.2.dist-info/RECORD
