Metadata-Version: 2.4
Name: df-compare-pl
Version: 0.2
Summary: compares two polars dataframes for equality
Author-email: jake greenhalgh <48000025+jbgreenh@users.noreply.github.com>
License-File: LICENSE
Requires-Python: <3.14,>=3.10
Requires-Dist: polars>=1.19.0
